typo_shot-0.1.2.data/scripts/typo
typo_shot-0.1.2.dist-info/top_level.txt
typo_shot-0.1.2.dist-info/RECORD
typo_shot-0.1.2.dist-info/DESCRIPTION.rst
typo_shot-0.1.2.dist-info/WHEEL
typo_shot-0.1.2.dist-info/METADATA
typo_shot-0.1.2.dist-info/metadata.json
typoshot/__init__.py
