Metadata-Version: 2.0
Name: typo-shot
Version: 0.1.2
Summary: Check your website/blog typography simple, with screenshots!
Home-page: https://github.com/flavertonrr/typo-shot
Author: Flaverton Rodrigues Rosa
Author-email: contato@flaverton.com
License: MIT
Keywords: splinter screenshot typo typography
Platform: UNKNOWN
Classifier: Topic :: Utilities
Classifier: License :: OSI Approved :: MIT License
Classifier: Programming Language :: Python
Classifier: Programming Language :: Python :: 2.7
Requires-Dist: splinter (>=0.7.3)
Requires-Dist: requests (>=2.4.3)
